n8n_cli/__init__.py
n8n_cli/client.py
n8n_cli/config.py
n8n_cli/exceptions.py
n8n_cli/main.py
n8n_cli/output.py
n8n_cli/py.typed
n8n_cli/commands/__init__.py
n8n_cli/commands/configure.py
n8n_cli/commands/create.py
n8n_cli/commands/delete.py
n8n_cli/commands/disable.py
n8n_cli/commands/enable.py
n8n_cli/commands/execution.py
n8n_cli/commands/executions.py
n8n_cli/commands/trigger.py
n8n_cli/commands/update.py
n8n_cli/commands/update_node.py
n8n_cli/commands/workflow.py
n8n_cli/commands/workflows.py
n8n_cli-0.3.6.dist-info/METADATA
n8n_cli-0.3.6.dist-info/WHEEL
n8n_cli-0.3.6.dist-info/entry_points.txt
n8n_cli-0.3.6.dist-info/licenses/LICENSE
n8n_cli-0.3.6.dist-info/RECORD
