Metadata-Version: 2.4
Name: n8n-cli
Version: 0.3.6
Summary: A command-line interface for interacting with n8n
Project-URL: Homepage, https://github.com/TidalStudio/n8n-cli
Project-URL: Documentation, https://github.com/TidalStudio/n8n-cli/wiki
Project-URL: Repository, https://github.com/TidalStudio/n8n-cli
Project-URL: Issues, https://github.com/TidalStudio/n8n-cli/issues
Author: TidalStudio
License-Expression: MIT
License-File: LICENSE
Keywords: automation,cli,n8n,workflow
Classifier: Development Status :: 3 - Alpha
Classifier: Environment :: Console
Classifier: Intended Audience :: Developers
Classifier: License :: OSI Approved :: MIT License
Classifier: Programming Language :: Python :: 3
Classifier: Programming Language :: Python :: 3.11
Classifier: Programming Language :: Python :: 3.12
Classifier: Programming Language :: Python :: 3.13
Requires-Python: >=3.11
Requires-Dist: click>=8.1.0
Requires-Dist: httpx>=0.27.0
Requires-Dist: rich>=13.0.0
Provides-Extra: dev
Requires-Dist: mypy>=1.13.0; extra == 'dev'
Requires-Dist: pytest-asyncio>=0.24.0; extra == 'dev'
Requires-Dist: pytest>=8.0.0; extra == 'dev'
Requires-Dist: ruff>=0.8.0; extra == 'dev'
